tx_rtl_files/max_count_gen.v
module max_count_gen (
	input wire [7:0] switches,
	output reg [27:0] max_count,
	output wire [15:0] segment_num_max,
	output wire [7:0] redundancy
);


reg [16:0] max_counter_samepacket = 17'd30;
// define speed & how fast
always @(switches) begin
	case (switches[3:0])
		4'b0000:	max_count <= 27'd124999999; // 1 pps
		4'b0001:	max_count <= 27'd62499999; // 2 pps
		4'b0010:	max_count <= 27'd12499999; // 10 pps
		4'b0011:	max_count <= 27'd6249999; //20 pps
		4'b0100:	max_count <= 27'd2499999; // 50 pps
		4'b0101:	max_count <= 27'd1249999; //100 pps
		4'b0110:	max_count <= 27'd624999; // 200pps
		4'b0111:	max_count <= 27'd249999; //500 pps
		4'b1000:	max_count <= 27'd124999; // 1000 pps
		4'b1001:	max_count <= 27'd62499; //2000 pps
		4'b1010:	max_count <= 27'd24999; //5000 pps
		4'b1011:	max_count <= 27'd12499; //10000 pps
		4'b1100:	max_count <= 27'd6249; //20000 pps
		4'b1101:	max_count <= 27'd2499; //50000 pps
		4'b1110:	max_count <= 27'd1249; //100000pps
		default:	max_count <= 27'd30; //ok? 
	endcase
	/*
	    case (switches[7:6])
        2'b00: max_counter_samepacket = 17'd30;
        2'b01: max_counter_samepacket = 17'd1249;   // 100000 pps
        2'b10: max_counter_samepacket = 17'd12499;  // 10000pps
        2'b11: max_counter_samepacket = 17'd124999; // 1000pps
     endcase
		*/
end

assign segment_num_max = (switches[7:6] == 2'b00) ? 1:
															switches[7:6] == 2'b01 ? 5:
															switches[7:6] == 2'b10 ? 121:
															switches[7:6] == 2'b11 ? 150 : 1;
assign redundancy = switches[5:4] == 2'b00 ? 1:
												switches[5:4] == 2'b01 ? 3:
												switches[5:4] == 2'b10 ? 5:
												switches[5:4] == 2'b11 ? 7 : 1;

endmodule

tx_rtl_files/send_control.v
/*
control output signals for byte_data
*/
module send_control(
	input wire clk125MHz,
	input wire RST,
	input wire [7:0] switches, 
	input wire busy,
	(* mark_debug = "true" *)	input wire start_frame,
	(* mark_debug = "true" *)	input wire oneframe_done,
	(* mark_debug = "true" *)	input wire maxdetect, 

	// output
	(* mark_debug = "true" *)	output reg [15:0] segment_num_inter = 0,
	(* mark_debug = "true" *)	output reg [7:0] txid_inter = 1,
	(* mark_debug = "true" *)	output wire [7:0] aux_inter,
	(* mark_debug = "true" *)	output reg start_sending = 0,
	output reg [15:0] segment_num_max,
	output wire hdmimode,
	(* mark_debug = "true" *) output wire framemode,
	output wire [7:0] redundancy 
);

reg [7:0] aux = 0;
reg [15:0] segment_num = 0;
reg [7:0] txid = 1;
wire [27:0] max_count;
assign hdmimode = (switches[3:0] == 4'b0000);
assign framemode = (switches[7:6] == 2'b11);


wire [15:0] segment_num_max_normal;
max_count_gen max_count_gen_i (
	.switches(switches[7:0]), //input
	.max_count(max_count), // output
	.segment_num_max(segment_num_max_normal), // output
	.redundancy(redundancy) // output
);
parameter segment_num_init = 0;

reg [27:0] count=0, counter_samepacket = 0;
reg in_sending = 0;

// like this:
/*
while (true) {
	for (id in 1..n) {
		if (id == 1) {
			for (segment_num in 0...m) {
				data = DATA_FROM_VIDEO_RAM;
				RAM[segment_num] = data;
				send_frame(data);
			}
		}
		else { 			//===== id != 2
			for (segment_num in 0...m) {
				data = RAM[segment_num];
				send_frame(data);
			}
		}
	}
	aux++;
}

*/
(* mark_debug = "true" *) reg [3:0] state = 0;
localparam state_wait = 0;
localparam state_id_1 = 1;
localparam state_id_not_1 = 2;
localparam state_id_1_sent = 3;
localparam state_id_not_1_sent = 4;
localparam state_wait_for_frame = 5;

(* mark_debug = "true" *) wire timer_done = (count == max_count);//hdmimode ? () : (count == max_count) ;

(* mark_debug = "true" *)reg [1:0] hdmistate = 0;
localparam hdmi_wait = 0;
localparam hdmi_sending = 1;
localparam hdmi_sent = 2;

wire [7:0] txid_next = (txid <= redundancy) ? txid + 1 : 1 ;
wire [15:0] segment_num_next = (segment_num < segment_num_max) ? segment_num + 1 : segment_num_init;
reg oneframe_done_detected;
(* mark_debug = "true" *) reg maxdetected = 0;
reg [15:0] segment_num_framemode;
reg [7:0] aux_base = 0, aux_base_inter = 0;

assign aux_inter = aux_base_inter + segment_num_inter;

always @(posedge clk125MHz) begin
	if (RST) begin
		hdmistate = 0;
		maxdetected = 0;
		segment_num_framemode = 0;
		oneframe_done_detected = 0;
		state = 0;
		segment_num = 0;
		txid = 0;
		count = 0;
		in_sending = 0;
		segment_num_inter = 0;
		txid_inter = 0;
		aux_base = 0;
		aux = 0;
		segment_num_max = 150;

	end else begin
		if (!framemode) begin
			segment_num_max <= segment_num_max_normal;
		end

		if (oneframe_done && hdmimode) begin // oneframe_done is used only HERE. now lock sareteru
			oneframe_done_detected <= 1'b1;
		end

		if (timer_done) begin
			count <= 0;
		end
		else
		if (!busy && (!hdmimode || (hdmimode && hdmistate != hdmi_sent))) begin
			count <= count + 1'b1;
		end else begin
			count <= 0;
		end

		if (txid_inter == 1 && maxdetect && !maxdetected) begin 
			segment_num_max <= segment_num_inter + 1;
			maxdetected <= 1'b1;
		end
		if (!busy)

		case (state)
			state_wait: begin
				if (!hdmimode) begin 
					state <= state_id_1;
					txid <= 1'b1;
					segment_num <= segment_num_init;
					aux <= 1'b0;
					
				end else begin // if hdmimode.
					if (start_frame) begin
						oneframe_done_detected <= 1'b0;
						state <= state_id_1;
						txid <= 1'b1;
						segment_num <= segment_num_init;
						hdmistate <= hdmi_sending;
					end
				end
			end

			state_id_1: begin
				if (hdmimode) begin
					if (start_frame) begin
						hdmistate <= hdmi_sending;
					end
				end
				if (framemode && !maxdetected) begin
					segment_num_max <= 150;
				end

				if (timer_done) begin
					if (!hdmimode) begin
						segment_num_inter <= segment_num;
						txid_inter <= 1'b1;
						aux_base_inter <= aux_base;
						//aux_inter <= aux;
						txid <= 1'b1;
						start_sending <= 1'b1;
						state <= state_id_1_sent;
					end
					else begin // hdmimode
						if (oneframe_done_detected) state <= state_id_1_sent;
						else
						if (hdmistate != hdmi_sent) begin
							segment_num_inter <= segment_num;
							txid_inter <= 1'b1;
							aux_base_inter <= aux_base;
							//aux_inter <= aux;
							txid <= 1'b1;
							start_sending <= 1'b1;
							state <= state_id_1_sent;
							hdmistate <= hdmi_sending;
						end
						else begin
							start_sending <= 1'b0;
						end
					end
				end 
				else begin 
					txid <= txid;
					aux <= aux;
					segment_num <= segment_num;
					start_sending <= 1'b0;
					end
			end // end of state_id_1
			
			state_id_1_sent: begin
				start_sending <= 1'b0;
				if (hdmimode && oneframe_done_detected && txid >= redundancy && segment_num >= segment_num_max - 1) begin
					oneframe_done_detected <= 1'b0;
					hdmistate <= hdmi_sent;
					state <= state_wait;
					aux <= aux + 1'b1;
					txid_inter <= 1'b1;
					segment_num <= segment_num_init;
				end else begin
					if (segment_num >= segment_num_max - 1) begin
						if (txid >= redundancy) begin
							state <= state_id_1;
							aux <= aux + 1;
							aux_base <= aux_base + segment_num_max;
							segment_num <= segment_num_init;
						end else begin
							state <= state_id_not_1;
							segment_num <= segment_num_init;
							txid <= txid_next;
							aux <= aux;
						end
					end
					else begin
						state <= state_id_1;
						segment_num <= segment_num_next;
					end
				end
			end

			state_id_not_1: begin
				if (timer_done) begin
					if (oneframe_done_detected) state <= state_id_not_1_sent;
					else begin
						segment_num_inter <= segment_num;
						txid_inter <= txid;
						start_sending <= 1'b1;
						aux_base_inter <= aux_base;
						state <= state_id_not_1_sent;
					end
				end
				else begin
					start_sending <= 1'b0;
				end
			end

			state_id_not_1_sent: begin
				start_sending <= 1'b0;
				maxdetected <= 1'b0;
				if (hdmimode && oneframe_done_detected && txid >=redundancy && segment_num >= segment_num_max - 1) begin
					oneframe_done_detected <= 1'b0;
					hdmistate <= hdmi_sent;
					state <= state_wait;
					aux <= aux + 1'b1;
					txid_inter <= 1'b1;
					aux_base <= aux_base + segment_num_max;
					segment_num <= segment_num_init;
				end else begin
					if (segment_num >= segment_num_max - 1) begin 
						if (txid == redundancy) begin
							state <= state_id_1;
							aux <= aux + 1'b1;
							aux_base <= aux_base + segment_num_max;
							segment_num <= segment_num_init;
							txid <= 1'b1;
						end
						else begin
							txid <= txid_next;
							segment_num <= segment_num_init;
							state <= state_id_not_1;
						end
					end
					else begin
						state <= state_id_not_1;
						segment_num <= segment_num_next;
					end
				end
			end
			// start_frame: start signal
			// oneframe_done: frame send signal
			/*
			state_wait_for_frame: begin
				if (start_frame) begin
					state <= state_id_1;
				end
			end
			*/
		endcase
	end
end
endmodule

txrx_rtl_files/tx_rtl_files/sim/tb_send_control.v
`timescale 1ns / 1ns
//`include "../send_control.v"
//`include "../max_count_gen.v"


module tb_send_control;

reg clk,busy,rst;
wire [15:0] segment_num;
wire [7:0] txid,txid_inter,aux;
wire start_sending;
reg start_frame, oneframe_done;

send_control uut(
	.clk125MHz(clk),
	.RST(rst),
//	.switches(8'b01010000),
//	.switches(8'b01011111),
	.switches(8'b01010000),
	.busy(busy),
	.start_frame(start_frame),
	.oneframe_done(oneframe_done),

	// output
	.segment_num_inter(segment_num),
	.txid_inter(txid_inter),
	.aux_inter(aux),
	.redundancy(),
	.start_sending(start_sending)
);

initial begin
	$dumpfile("send_control.vcd");
	$dumpvars(0,tb_send_control);
end

initial begin
	clk = 0;
	busy = 0;
	oneframe_done = 0;
	start_frame = 0;
	rst=0;
	#20;
	start_frame = 1;
	#8;
	start_frame = 0;
	#4000;
	oneframe_done = 1;
	#8;
	oneframe_done = 0;

	#4000;// stop here.
	#20;
	start_frame = 1;
	#8;
	start_frame = 0;
	#4000;
	oneframe_done = 1;
	#8;
	oneframe_done = 0;
	#2000;
	$finish;
end

always #4 begin
	clk <= !clk;
end



endmodule

txrx_rtl_files/tx_rtl_files/sim/send_control.vcd
$date
	Mon Apr 15 16:09:26 2019
$end
$version
	Icarus Verilog
$end
$timescale
	1ps
$end
$scope module tb_send_control $end
$var wire 8 ! txid_inter [7:0] $end
$var wire 1 " start_sending $end
$var wire 16 # segment_num [15:0] $end
$var wire 8 $ aux [7:0] $end
$var reg 1 % busy $end
$var reg 1 & clk $end
$var reg 1 ' oneframe_done $end
$var reg 1 ( rst $end
$var reg 1 ) start_frame $end
$scope module uut $end
$var wire 1 ( RST $end
$var wire 1 % busy $end
$var wire 1 & clk125MHz $end
$var wire 1 * maxdetect $end
$var wire 1 ' oneframe_done $end
$var wire 1 ) start_frame $end
$var wire 8 + switches [7:0] $end
$var wire 8 , txid_next [7:0] $end
$var wire 1 - timer_done $end
$var wire 16 . segment_num_next [15:0] $end
$var wire 16 / segment_num_max_normal [15:0] $end
$var wire 8 0 redundancy [7:0] $end
$var wire 28 1 max_count [27:0] $end
$var wire 1 2 hdmimode $end
$var wire 1 3 framemode $end
$var wire 8 4 aux_inter [7:0] $end
$var reg 8 5 aux [7:0] $end
$var reg 8 6 aux_base [7:0] $end
$var reg 8 7 aux_base_inter [7:0] $end
$var reg 28 8 count [27:0] $end
$var reg 28 9 counter_samepacket [27:0] $end
$var reg 2 : hdmistate [1:0] $end
$var reg 1 ; in_sending $end
$var reg 1 < maxdetected $end
$var reg 1 = oneframe_done_detected $end
$var reg 16 > segment_num [15:0] $end
$var reg 16 ? segment_num_framemode [15:0] $end
$var reg 16 @ segment_num_inter [15:0] $end
$var reg 16 A segment_num_max [15:0] $end
$var reg 1 " start_sending $end
$var reg 4 B state [3:0] $end
$var reg 8 C txid [7:0] $end
$var reg 8 D txid_inter [7:0] $end
$scope module max_count_gen_i $end
$var wire 8 E switches [7:0] $end
$var wire 16 F segment_num_max [15:0] $end
$var wire 8 G redundancy [7:0] $end
$var reg 28 H max_count [27:0] $end
$var reg 17 I max_counter_samepacket [16:0] $end
$upscope $end
$upscope $end
$upscope $end
$enddefinitions $end
#0
$dumpvars
b110010 I
b11110 H
b11 G
b11 F
b1010000 E
b1 D
b1 C
b0 B
bx A
b0 @
bx ?
b0 >
x=
0<
0;
b0 :
b0 9
b0 8
b0 7
b0 6
b0 5
b0 4
03
12
b11110 1
b11 0
b11 /
b0x .
0-
b10 ,
b1010000 +
z*
0)
0(
0'
0&
0%
b0 $
b0 #
0"
b1 !
$end
#4000
b1 .
b1 8
b11 A
1&
#8000
0&
#12000
b10 8
1&
#16000
0&
#20000
b1 :
b1 B
0=
b11 8
1&
1)
#24000
0&
#28000
b100 8
1&
0)
#32000
0&
#36000
b101 8
1&
#40000
0&
#44000
b110 8
1&
#48000
0&
#52000
b111 8
1&
#56000
0&
#60000
b1000 8
1&
#64000
0&
#68000
b1001 8
1&
#72000
0&
#76000
b1010 8
1&
#80000
0&
#84000
b1011 8
1&
#88000
0&
#92000
b1100 8
1&
#96000
0&
#100000
b1101 8
1&
#104000
0&
#108000
b1110 8
1&
#112000
0&
#116000
b1111 8
1&
#120000
0&
#124000
b10000 8
1&
#128000
0&
#132000
b10001 8
1&
#136000
0&
#140000
b10010 8
1&
#144000
0&
#148000
b10011 8
1&
#152000
0&
#156000
b10100 8
1&
#160000
0&
#164000
b10101 8
1&
#168000
0&
#172000
b10110 8
1&
#176000
0&
#180000
b10111 8
1&
#184000
0&
#188000
b11000 8
1&
#192000
0&
#196000
b11001 8
1&
#200000
0&
#204000
b11010 8
1&
#208000
0&
#212000
b11011 8
1&
#216000
0&
#220000
b11100 8
1&
#224000
0&
#228000
b11101 8
1&
#232000
0&
#236000
1-
b11110 8
1&
#240000
0&
#244000
b11 B
1"
0-
b0 8
1&
#248000
0&
#252000
b10 .
b1 >
b1 B
0"
b1 8
1&
#256000
0&
#260000
b10 8
1&
#264000
0&
#268000
b11 8
1&
#272000
0&
#276000
b100 8
1&
#280000
0&
#284000
b101 8
1&
#288000
0&
#292000
b110 8
1&
#296000
0&
#300000
b111 8
1&
#304000
0&
#308000
b1000 8
1&
#312000
0&
#316000
b1001 8
1&
#320000
0&
#324000
b1010 8
1&
#328000
0&
#332000
b1011 8
1&
#336000
0&
#340000
b1100 8
1&
#344000
0&
#348000
b1101 8
1&
#352000
0&
#356000
b1110 8
1&
#360000
0&
#364000
b1111 8
1&
#368000
0&
#372000
b10000 8
1&
#376000
0&
#380000
b10001 8
1&
#384000
0&
#388000
b10010 8
1&
#392000
0&
#396000
b10011 8
1&
#400000
0&
#404000
b10100 8
1&
#408000
0&
#412000
b10101 8
1&
#416000
0&
#420000
b10110 8
1&
#424000
0&
#428000
b10111 8
1&
#432000
0&
#436000
b11000 8
1&
#440000
0&
#444000
b11001 8
1&
#448000
0&
#452000
b11010 8
1&
#456000
0&
#460000
b11011 8
1&
#464000
0&
#468000
b11100 8
1&
#472000
0&
#476000
b11101 8
1&
#480000
0&
#484000
1-
b11110 8
1&
#488000
0&
#492000
b1 $
b1 4
b11 B
1"
b1 #
b1 @
0-
b0 8
1&
#496000
0&
#500000
b11 .
b10 >
b1 B
0"
b1 8
1&
#504000
0&
#508000
b10 8
1&
#512000
0&
#516000
b11 8
1&
#520000
0&
#524000
b100 8
1&
#528000
0&
#532000
b101 8
1&
#536000
0&
#540000
b110 8
1&
#544000
0&
#548000
b111 8
1&
#552000
0&
#556000
b1000 8
1&
#560000
0&
#564000
b1001 8
1&
#568000
0&
#572000
b1010 8
1&
#576000
0&
#580000
b1011 8
1&
#584000
0&
#588000
b1100 8
1&
#592000
0&
#596000
b1101 8
1&
#600000
0&
#604000
b1110 8
1&
#608000
0&
#612000
b1111 8
1&
#616000
0&
#620000
b10000 8
1&
#624000
0&
#628000
b10001 8
1&
#632000
0&
#636000
b10010 8
1&
#640000
0&
#644000
b10011 8
1&
#648000
0&
#652000
b10100 8
1&
#656000
0&
#660000
b10101 8
1&
#664000
0&
#668000
b10110 8
1&
#672000
0&
#676000
b10111 8
1&
#680000
0&
#684000
b11000 8
1&
#688000
0&
#692000
b11001 8
1&
#696000
0&
#700000
b11010 8
1&
#704000
0&
#708000
b11011 8
1&
#712000
0&
#716000
b11100 8
1&
#720000
0&
#724000
b11101 8
1&
#728000
0&
#732000
1-
b11110 8
1&
#736000
0&
#740000
b10 $
b10 4
b11 B
1"
b10 #
b10 @
0-
b0 8
1&
#744000
0&
#748000
b1 .
b11 ,
b10 C
b0 >
b10 B
0"
b1 8
1&
#752000
0&
#756000
b10 8
1&
#760000
0&
#764000
b11 8
1&
#768000
0&
#772000
b100 8
1&
#776000
0&
#780000
b101 8
1&
#784000
0&
#788000
b110 8
1&
#792000
0&
#796000
b111 8
1&
#800000
0&
#804000
b1000 8
1&
#808000
0&
#812000
b1001 8
1&
#816000
0&
#820000
b1010 8
1&
#824000
0&
#828000
b1011 8
1&
#832000
0&
#836000
b1100 8
1&
#840000
0&
#844000
b1101 8
1&
#848000
0&
#852000
b1110 8
1&
#856000
0&
#860000
b1111 8
1&
#864000
0&
#868000
b10000 8
1&
#872000
0&
#876000
b10001 8
1&
#880000
0&
#884000
b10010 8
1&
#888000
0&
#892000
b10011 8
1&
#896000
0&
#900000
b10100 8
1&
#904000
0&
#908000
b10101 8
1&
#912000
0&
#916000
b10110 8
1&
#920000
0&
#924000
b10111 8
1&
#928000
0&
#932000
b11000 8
1&
#936000
0&
#940000
b11001 8
1&
#944000
0&
#948000
b11010 8
1&
#952000
0&
#956000
b11011 8
1&
#960000
0&
#964000
b11100 8
1&
#968000
0&
#972000
b11101 8
1&
#976000
0&
#980000
1-
b11110 8
1&
#984000
0&
#988000
b0 $
b0 4
b100 B
1"
b10 !
b10 D
b0 #
b0 @
0-
b0 8
1&
#992000
0&
#996000
b10 .
b1 >
b10 B
0"
b1 8
1&
#1000000
0&
#1004000
b10 8
1&
#1008000
0&
#1012000
b11 8
1&
#1016000
0&
#1020000
b100 8
1&
#1024000
0&
#1028000
b101 8
1&
#1032000
0&
#1036000
b110 8
1&
#1040000
0&
#1044000
b111 8
1&
#1048000
0&
#1052000
b1000 8
1&
#1056000
0&
#1060000
b1001 8
1&
#1064000
0&
#1068000
b1010 8
1&
#1072000
0&
#1076000
b1011 8
1&
#1080000
0&
#1084000
b1100 8
1&
#1088000
0&
#1092000
b1101 8
1&
#1096000
0&
#1100000
b1110 8
1&
#1104000
0&
#1108000
b1111 8
1&
#1112000
0&
#1116000
b10000 8
1&
#1120000
0&
#1124000
b10001 8
1&
#1128000
0&
#1132000
b10010 8
1&
#1136000
0&
#1140000
b10011 8
1&
#1144000
0&
#1148000
b10100 8
1&
#1152000
0&
#1156000
b10101 8
1&
#1160000
0&
#1164000
b10110 8
1&
#1168000
0&
#1172000
b10111 8
1&
#1176000
0&
#1180000
b11000 8
1&
#1184000
0&
#1188000
b11001 8
1&
#1192000
0&
#1196000
b11010 8
1&
#1200000
0&
#1204000
b11011 8
1&
#1208000
0&
#1212000
b11100 8
1&
#1216000
0&
#1220000
b11101 8
1&
#1224000
0&
#1228000
1-
b11110 8
1&
#1232000
0&
#1236000
b1 $
b1 4
b100 B
1"
b1 #
b1 @
0-
b0 8
1&
#1240000
0&
#1244000
b11 .
b10 >
b10 B
0"
b1 8
1&
#1248000
0&
#1252000
b10 8
1&
#1256000
0&
#1260000
b11 8
1&
#1264000
0&
#1268000
b100 8
1&
#1272000
0&
#1276000
b101 8
1&
#1280000
0&
#1284000
b110 8
1&
#1288000
0&
#1292000
b111 8
1&
#1296000
0&
#1300000
b1000 8
1&
#1304000
0&
#1308000
b1001 8
1&
#1312000
0&
#1316000
b1010 8
1&
#1320000
0&
#1324000
b1011 8
1&
#1328000
0&
#1332000
b1100 8
1&
#1336000
0&
#1340000
b1101 8
1&
#1344000
0&
#1348000
b1110 8
1&
#1352000
0&
#1356000
b1111 8
1&
#1360000
0&
#1364000
b10000 8
1&
#1368000
0&
#1372000
b10001 8
1&
#1376000
0&
#1380000
b10010 8
1&
#1384000
0&
#1388000
b10011 8
1&
#1392000
0&
#1396000
b10100 8
1&
#1400000
0&
#1404000
b10101 8
1&
#1408000
0&
#1412000
b10110 8
1&
#1416000
0&
#1420000
b10111 8
1&
#1424000
0&
#1428000
b11000 8
1&
#1432000
0&
#1436000
b11001 8
1&
#1440000
0&
#1444000
b11010 8
1&
#1448000
0&
#1452000
b11011 8
1&
#1456000
0&
#1460000
b11100 8
1&
#1464000
0&
#1468000
b11101 8
1&
#1472000
0&
#1476000
1-
b11110 8
1&
#1480000
0&
#1484000
b10 $
b10 4
b100 B
1"
b10 #
b10 @
0-
b0 8
1&
#1488000
0&
#1492000
b1 .
b100 ,
b10 B
b0 >
b11 C
0"
b1 8
1&
#1496000
0&
#1500000
b10 8
1&
#1504000
0&
#1508000
b11 8
1&
#1512000
0&
#1516000
b100 8
1&
#1520000
0&
#1524000
b101 8
1&
#1528000
0&
#1532000
b110 8
1&
#1536000
0&
#1540000
b111 8
1&
#1544000
0&
#1548000
b1000 8
1&
#1552000
0&
#1556000
b1001 8
1&
#1560000
0&
#1564000
b1010 8
1&
#1568000
0&
#1572000
b1011 8
1&
#1576000
0&
#1580000
b1100 8
1&
#1584000
0&
#1588000
b1101 8
1&
#1592000
0&
#1596000
b1110 8
1&
#1600000
0&
#1604000
b1111 8
1&
#1608000
0&
#1612000
b10000 8
1&
#1616000
0&
#1620000
b10001 8
1&
#1624000
0&
#1628000
b10010 8
1&
#1632000
0&
#1636000
b10011 8
1&
#1640000
0&
#1644000
b10100 8
1&
#1648000
0&
#1652000
b10101 8
1&
#1656000
0&
#1660000
b10110 8
1&
#1664000
0&
#1668000
b10111 8
1&
#1672000
0&
#1676000
b11000 8
1&
#1680000
0&
#1684000
b11001 8
1&
#1688000
0&
#1692000
b11010 8
1&
#1696000
0&
#1700000
b11011 8
1&
#1704000
0&
#1708000
b11100 8
1&
#1712000
0&
#1716000
b11101 8
1&
#1720000
0&
#1724000
1-
b11110 8
1&
#1728000
0&
#1732000
b0 $
b0 4
b100 B
1"
b11 !
b11 D
b0 #
b0 @
0-
b0 8
1&
#1736000
0&
#1740000
b10 .
b1 >
b10 B
0"
b1 8
1&
#1744000
0&
#1748000
b10 8
1&
#1752000
0&
#1756000
b11 8
1&
#1760000
0&
#1764000
b100 8
1&
#1768000
0&
#1772000
b101 8
1&
#1776000
0&
#1780000
b110 8
1&
#1784000
0&
#1788000
b111 8
1&
#1792000
0&
#1796000
b1000 8
1&
#1800000
0&
#1804000
b1001 8
1&
#1808000
0&
#1812000
b1010 8
1&
#1816000
0&
#1820000
b1011 8
1&
#1824000
0&
#1828000
b1100 8
1&
#1832000
0&
#1836000
b1101 8
1&
#1840000
0&
#1844000
b1110 8
1&
#1848000
0&
#1852000
b1111 8
1&
#1856000
0&
#1860000
b10000 8
1&
#1864000
0&
#1868000
b10001 8
1&
#1872000
0&
#1876000
b10010 8
1&
#1880000
0&
#1884000
b10011 8
1&
#1888000
0&
#1892000
b10100 8
1&
#1896000
0&
#1900000
b10101 8
1&
#1904000
0&
#1908000
b10110 8
1&
#1912000
0&
#1916000
b10111 8
1&
#1920000
0&
#1924000
b11000 8
1&
#1928000
0&
#1932000
b11001 8
1&
#1936000
0&
#1940000
b11010 8
1&
#1944000
0&
#1948000
b11011 8
1&
#1952000
0&
#1956000
b11100 8
1&
#1960000
0&
#1964000
b11101 8
1&
#1968000
0&
#1972000
1-
b11110 8
1&
#1976000
0&
#1980000
b1 $
b1 4
b100 B
1"
b1 #
b1 @
0-
b0 8
1&
#1984000
0&
#1988000
b11 .
b10 >
b10 B
0"
b1 8
1&
#1992000
0&
#1996000
b10 8
1&
#2000000
0&
#2004000
b11 8
1&
#2008000
0&
#2012000
b100 8
1&
#2016000
0&
#2020000
b101 8
1&
#2024000
0&
#2028000
b110 8
1&
#2032000
0&
#2036000
b111 8
1&
#2040000
0&
#2044000
b1000 8
1&
#2048000
0&
#2052000
b1001 8
1&
#2056000
0&
#2060000
b1010 8
1&
#2064000
0&
#2068000
b1011 8
1&
#2072000
0&
#2076000
b1100 8
1&
#2080000
0&
#2084000
b1101 8
1&
#2088000
0&
#2092000
b1110 8
1&
#2096000
0&
#2100000
b1111 8
1&
#2104000
0&
#2108000
b10000 8
1&
#2112000
0&
#2116000
b10001 8
1&
#2120000
0&
#2124000
b10010 8
1&
#2128000
0&
#2132000
b10011 8
1&
#2136000
0&
#2140000
b10100 8
1&
#2144000
0&
#2148000
b10101 8
1&
#2152000
0&
#2156000
b10110 8
1&
#2160000
0&
#2164000
b10111 8
1&
#2168000
0&
#2172000
b11000 8
1&
#2176000
0&
#2180000
b11001 8
1&
#2184000
0&
#2188000
b11010 8
1&
#2192000
0&
#2196000
b11011 8
1&
#2200000
0&
#2204000
b11100 8
1&
#2208000
0&
#2212000
b11101 8
1&
#2216000
0&
#2220000
1-
b11110 8
1&
#2224000
0&
#2228000
b10 $
b10 4
b100 B
1"
b10 #
b10 @
0-
b0 8
1&
#2232000
0&
#2236000
b1 .
b10 ,
b1 C
b0 >
b11 6
b1 5
b1 B
0"
b1 8
1&
#2240000
0&
#2244000
b10 8
1&
#2248000
0&
#2252000
b11 8
1&
#2256000
0&
#2260000
b100 8
1&
#2264000
0&
#2268000
b101 8
1&
#2272000
0&
#2276000
b110 8
1&
#2280000
0&
#2284000
b111 8
1&
#2288000
0&
#2292000
b1000 8
1&
#2296000
0&
#2300000
b1001 8
1&
#2304000
0&
#2308000
b1010 8
1&
#2312000
0&
#2316000
b1011 8
1&
#2320000
0&
#2324000
b1100 8
1&
#2328000
0&
#2332000
b1101 8
1&
#2336000
0&
#2340000
b1110 8
1&
#2344000
0&
#2348000
b1111 8
1&
#2352000
0&
#2356000
b10000 8
1&
#2360000
0&
#2364000
b10001 8
1&
#2368000
0&
#2372000
b10010 8
1&
#2376000
0&
#2380000
b10011 8
1&
#2384000
0&
#2388000
b10100 8
1&
#2392000
0&
#2396000
b10101 8
1&
#2400000
0&
#2404000
b10110 8
1&
#2408000
0&
#2412000
b10111 8
1&
#2416000
0&
#2420000
b11000 8
1&
#2424000
0&
#2428000
b11001 8
1&
#2432000
0&
#2436000
b11010 8
1&
#2440000
0&
#2444000
b11011 8
1&
#2448000
0&
#2452000
b11100 8
1&
#2456000
0&
#2460000
b11101 8
1&
#2464000
0&
#2468000
1-
b11110 8
1&
#2472000
0&
#2476000
b11 $
b11 4
b11 B
1"
b11 7
b1 !
b1 D
b0 #
b0 @
0-
b0 8
1&
#2480000
0&
#2484000
b10 .
b1 >
b1 B
0"
b1 8
1&
#2488000
0&
#2492000
b10 8
1&
#2496000
0&
#2500000
b11 8
1&
#2504000
0&
#2508000
b100 8
1&
#2512000
0&
#2516000
b101 8
1&
#2520000
0&
#2524000
b110 8
1&
#2528000
0&
#2532000
b111 8
1&
#2536000
0&
#2540000
b1000 8
1&
#2544000
0&
#2548000
b1001 8
1&
#2552000
0&
#2556000
b1010 8
1&
#2560000
0&
#2564000
b1011 8
1&
#2568000
0&
#2572000
b1100 8
1&
#2576000
0&
#2580000
b1101 8
1&
#2584000
0&
#2588000
b1110 8
1&
#2592000
0&
#2596000
b1111 8
1&
#2600000
0&
#2604000
b10000 8
1&
#2608000
0&
#2612000
b10001 8
1&
#2616000
0&
#2620000
b10010 8
1&
#2624000
0&
#2628000
b10011 8
1&
#2632000
0&
#2636000
b10100 8
1&
#2640000
0&
#2644000
b10101 8
1&
#2648000
0&
#2652000
b10110 8
1&
#2656000
0&
#2660000
b10111 8
1&
#2664000
0&
#2668000
b11000 8
1&
#2672000
0&
#2676000
b11001 8
1&
#2680000
0&
#2684000
b11010 8
1&
#2688000
0&
#2692000
b11011 8
1&
#2696000
0&
#2700000
b11100 8
1&
#2704000
0&
#2708000
b11101 8
1&
#2712000
0&
#2716000
1-
b11110 8
1&
#2720000
0&
#2724000
b100 $
b100 4
b11 B
1"
b1 #
b1 @
0-
b0 8
1&
#2728000
0&
#2732000
b11 .
b10 >
b1 B
0"
b1 8
1&
#2736000
0&
#2740000
b10 8
1&
#2744000
0&
#2748000
b11 8
1&
#2752000
0&
#2756000
b100 8
1&
#2760000
0&
#2764000
b101 8
1&
#2768000
0&
#2772000
b110 8
1&
#2776000
0&
#2780000
b111 8
1&
#2784000
0&
#2788000
b1000 8
1&
#2792000
0&
#2796000
b1001 8
1&
#2800000
0&
#2804000
b1010 8
1&
#2808000
0&
#2812000
b1011 8
1&
#2816000
0&
#2820000
b1100 8
1&
#2824000
0&
#2828000
b1101 8
1&
#2832000
0&
#2836000
b1110 8
1&
#2840000
0&
#2844000
b1111 8
1&
#2848000
0&
#2852000
b10000 8
1&
#2856000
0&
#2860000
b10001 8
1&
#2864000
0&
#2868000
b10010 8
1&
#2872000
0&
#2876000
b10011 8
1&
#2880000
0&
#2884000
b10100 8
1&
#2888000
0&
#2892000
b10101 8
1&
#2896000
0&
#2900000
b10110 8
1&
#2904000
0&
#2908000
b10111 8
1&
#2912000
0&
#2916000
b11000 8
1&
#2920000
0&
#2924000
b11001 8
1&
#2928000
0&
#2932000
b11010 8
1&
#2936000
0&
#2940000
b11011 8
1&
#2944000
0&
#2948000
b11100 8
1&
#2952000
0&
#2956000
b11101 8
1&
#2960000
0&
#2964000
1-
b11110 8
1&
#2968000
0&
#2972000
b101 $
b101 4
b11 B
1"
b10 #
b10 @
0-
b0 8
1&
#2976000
0&
#2980000
b1 .
b11 ,
b10 C
b0 >
b10 B
0"
b1 8
1&
#2984000
0&
#2988000
b10 8
1&
#2992000
0&
#2996000
b11 8
1&
#3000000
0&
#3004000
b100 8
1&
#3008000
0&
#3012000
b101 8
1&
#3016000
0&
#3020000
b110 8
1&
#3024000
0&
#3028000
b111 8
1&
#3032000
0&
#3036000
b1000 8
1&
#3040000
0&
#3044000
b1001 8
1&
#3048000
0&
#3052000
b1010 8
1&
#3056000
0&
#3060000
b1011 8
1&
#3064000
0&
#3068000
b1100 8
1&
#3072000
0&
#3076000
b1101 8
1&
#3080000
0&
#3084000
b1110 8
1&
#3088000
0&
#3092000
b1111 8
1&
#3096000
0&
